EasyReport/__init__.py
EasyReport/easy_report.py
EasyReport-0.0.7.dist-info/LICENSE
EasyReport-0.0.7.dist-info/METADATA
EasyReport-0.0.7.dist-info/WHEEL
EasyReport-0.0.7.dist-info/top_level.txt
EasyReport-0.0.7.dist-info/RECORD
