Metadata-Version: 2.1
Name: EasyReport
Version: 0.0.7
Summary: Generate a quick EDA report of a pandas DataFrame
Home-page: https://github.com/Sumegh20/EasyReport
Author: Sumegh Sen
Author-email: sumegh20@gmail.com
License: UNKNOWN
Project-URL: Bug Tracker, https://github.com/Sumegh20/EasyReport/issues
Keywords: EDA,Exploratory Data Analysis,Easy Report,Dataset Report
Platform: UNKNOWN
Classifier: Programming Language :: Python :: 3
Classifier: License :: OSI Approved :: MIT License
Classifier: Operating System :: OS Independent
Requires-Python: >=3.6
License-File: LICENSE
Requires-Dist: pandas (==1.1.5)
Requires-Dist: seaborn (==0.11.2)
Requires-Dist: scipy (==1.5.4)
Requires-Dist: matplotlib (==3.3.4)
Requires-Dist: missingno (==0.5.0)
